tumeryk_ai_trust_score/__init__.py
tumeryk_ai_trust_score/trust_score_client.py
tumeryk_ai_trust_score-0.1.0.dist-info/METADATA
tumeryk_ai_trust_score-0.1.0.dist-info/WHEEL
tumeryk_ai_trust_score-0.1.0.dist-info/licenses/LICENSE
tumeryk_ai_trust_score-0.1.0.dist-info/RECORD
