Metadata-Version: 2.4
Name: tumeryk-ai-trust-score
Version: 0.1.0
Summary: A Python client for accessing the Tumeryk AI Trust Score API
Project-URL: Homepage, https://tmryk.com
Project-URL: Bug Tracker, https://github.com/tumeryk/tumeryk-ai-trust-score/issues
Project-URL: Documentation, https://docs.tmryk.com
Project-URL: Source Code, https://github.com/tumeryk/tumeryk-ai-trust-score
Author-email: Tumeryk <support@tmryk.com>
License-File: LICENSE
Classifier: Development Status :: 4 - Beta
Classifier: Intended Audience :: Developers
Classifier: License :: OSI Approved :: MIT License
Classifier: Operating System :: OS Independent
Classifier: Programming Language :: Python :: 3
Classifier: Programming Language :: Python :: 3.7
Classifier: Programming Language :: Python :: 3.8
Classifier: Programming Language :: Python :: 3.9
Classifier: Programming Language :: Python :: 3.10
Classifier: Programming Language :: Python :: 3.11
Classifier: Topic :: Scientific/Engineering :: Artificial Intelligence
Classifier: Topic :: Security
Classifier: Topic :: Software Development :: Libraries :: Python Modules
Requires-Python: >=3.7
Requires-Dist: requests>=2.31.0
